hotrod.py
hotrod-0.1.dist-info/LICENSE
hotrod-0.1.dist-info/WHEEL
hotrod-0.1.dist-info/METADATA
hotrod-0.1.dist-info/RECORD
