Metadata-Version: 2.1
Name: hotrod
Version: 0.1
Summary: 1D thermal modeling done fast.
Home-page: https://github.com/michaelaye/hotrod
License: UNKNOWN
Author: Michael Aye
Author-email: kmichael.aye@gmail.com
Classifier: License :: OSI Approved :: MIT License
